{
  "$schema": "https://raw.githubusercontent.com/spdx/spdx-spec/v2.2.1/schemas/spdx-schema.json",
  "spdxVersion": "SPDX-2.2",
  "dataLicense": "CC0-1.0",
  "SPDXID": "SPDXRef-DOCUMENT",
  "documentNamespace": "https://spdx.org/spdxdocs/zlib-x64-windows-1.2.13-22b86231-0587-457e-a203-928f350293d6",
  "name": "zlib:x64-windows@1.2.13 10d5b0222065edd11cc46913e9209aaab0707fab3172070544cc2db551455d4d",
  "creationInfo": {
    "creators": [
      "Tool: vcpkg-2025-11-19-da1f056dc0775ac651bea7e3fbbf4066146a55f3"
    ],
    "created": "2025-12-29T08:44:10Z"
  },
  "relationships": [
    {
      "spdxElementId": "SPDXRef-port",
      "relationshipType": "GENERATES",
      "relatedSpdxElement": "SPDXRef-binary"
    },
    {
      "spdxElementId": "SPDXRef-port",
      "relationshipType": "CONTAINS",
      "relatedSpdxElement": "SPDXRef-port-file-0"
    },
    {
      "spdxElementId": "SPDXRef-port",
      "relationshipType": "CONTAINS",
      "relatedSpdxElement": "SPDXRef-port-file-1"
    },
    {
      "spdxElementId": "SPDXRef-port",
      "relationshipType": "CONTAINS",
      "relatedSpdxElement": "SPDXRef-port-file-2"
    },
    {
      "spdxElementId": "SPDXRef-port",
      "relationshipType": "CONTAINS",
      "relatedSpdxElement": "SPDXRef-port-file-3"
    },
    {
      "spdxElementId": "SPDXRef-port",
      "relationshipType": "CONTAINS",
      "relatedSpdxElement": "SPDXRef-port-file-4"
    },
    {
      "spdxElementId": "SPDXRef-port",
      "relationshipType": "CONTAINS",
      "relatedSpdxElement": "SPDXRef-port-file-5"
    },
    {
      "spdxElementId": "SPDXRef-port",
      "relationshipType": "CONTAINS",
      "relatedSpdxElement": "SPDXRef-port-file-6"
    },
    {
      "spdxElementId": "SPDXRef-port",
      "relationshipType": "CONTAINS",
      "relatedSpdxElement": "SPDXRef-port-file-7"
    },
    {
      "spdxElementId": "SPDXRef-port-file-7",
      "relationshipType": "DEPENDENCY_MANIFEST_OF",
      "relatedSpdxElement": "SPDXRef-port"
    },
    {
      "spdxElementId": "SPDXRef-binary",
      "relationshipType": "CONTAINS",
      "relatedSpdxElement": "SPDXRef-binary-file-0"
    },
    {
      "spdxElementId": "SPDXRef-binary",
      "relationshipType": "CONTAINS",
      "relatedSpdxElement": "SPDXRef-binary-file-1"
    },
    {
      "spdxElementId": "SPDXRef-binary",
      "relationshipType": "CONTAINS",
      "relatedSpdxElement": "SPDXRef-binary-file-2"
    },
    {
      "spdxElementId": "SPDXRef-binary",
      "relationshipType": "CONTAINS",
      "relatedSpdxElement": "SPDXRef-binary-file-3"
    },
    {
      "spdxElementId": "SPDXRef-binary",
      "relationshipType": "CONTAINS",
      "relatedSpdxElement": "SPDXRef-binary-file-4"
    },
    {
      "spdxElementId": "SPDXRef-binary",
      "relationshipType": "CONTAINS",
      "relatedSpdxElement": "SPDXRef-binary-file-5"
    },
    {
      "spdxElementId": "SPDXRef-binary",
      "relationshipType": "CONTAINS",
      "relatedSpdxElement": "SPDXRef-binary-file-6"
    },
    {
      "spdxElementId": "SPDXRef-binary",
      "relationshipType": "CONTAINS",
      "relatedSpdxElement": "SPDXRef-binary-file-7"
    },
    {
      "spdxElementId": "SPDXRef-binary",
      "relationshipType": "CONTAINS",
      "relatedSpdxElement": "SPDXRef-binary-file-8"
    },
    {
      "spdxElementId": "SPDXRef-binary",
      "relationshipType": "CONTAINS",
      "relatedSpdxElement": "SPDXRef-binary-file-9"
    },
    {
      "spdxElementId": "SPDXRef-binary",
      "relationshipType": "CONTAINS",
      "relatedSpdxElement": "SPDXRef-binary-file-10"
    },
    {
      "spdxElementId": "SPDXRef-binary",
      "relationshipType": "CONTAINS",
      "relatedSpdxElement": "SPDXRef-binary-file-11"
    },
    {
      "spdxElementId": "SPDXRef-binary",
      "relationshipType": "CONTAINS",
      "relatedSpdxElement": "SPDXRef-binary-file-12"
    },
    {
      "spdxElementId": "SPDXRef-binary",
      "relationshipType": "CONTAINS",
      "relatedSpdxElement": "SPDXRef-binary-file-13"
    }
  ],
  "packages": [
    {
      "name": "zlib",
      "SPDXID": "SPDXRef-port",
      "versionInfo": "1.2.13",
      "downloadLocation": "git+https://github.com/Microsoft/vcpkg@ad5a49006f73b45b715299515f31164131b51982",
      "homepage": "https://www.zlib.net/",
      "licenseConcluded": "Zlib",
      "licenseDeclared": "NOASSERTION",
      "copyrightText": "NOASSERTION",
      "description": "A compression library",
      "comment": "This is the port (recipe) consumed by vcpkg."
    },
    {
      "name": "zlib:x64-windows",
      "SPDXID": "SPDXRef-binary",
      "versionInfo": "10d5b0222065edd11cc46913e9209aaab0707fab3172070544cc2db551455d4d",
      "downloadLocation": "NONE",
      "licenseConcluded": "Zlib",
      "licenseDeclared": "NOASSERTION",
      "copyrightText": "NOASSERTION",
      "comment": "This is a binary package built by vcpkg."
    },
    {
      "SPDXID": "SPDXRef-resource-0",
      "name": "madler/zlib",
      "downloadLocation": "git+https://github.com/madler/zlib@v1.2.13",
      "licenseConcluded": "NOASSERTION",
      "licenseDeclared": "NOASSERTION",
      "copyrightText": "NOASSERTION",
      "checksums": [
        {
          "algorithm": "SHA512",
          "checksumValue": "44b834fbfb50cca229209b8dbe1f96b258f19a49f5df23b80970b716371d856a4adf525edb4c6e0e645b180ea949cb90f5365a1d896160f297f56794dd888659"
        }
      ]
    }
  ],
  "files": [
    {
      "fileName": "./0001-Prevent-invalid-inclusions-when-HAVE_-is-set-to-0.patch",
      "SPDXID": "SPDXRef-port-file-0",
      "checksums": [
        {
          "algorithm": "SHA256",
          "checksumValue": "750b9542cb55e6328cca01d3ca997f1373b9530afa95e04213168676936e7bfa"
        }
      ],
      "licenseConcluded": "NOASSERTION",
      "copyrightText": "NOASSERTION"
    },
    {
      "fileName": "./0002-skip-building-examples.patch",
      "SPDXID": "SPDXRef-port-file-1",
      "checksums": [
        {
          "algorithm": "SHA256",
          "checksumValue": "835ddecfed752e0f49be9b0f8ff7ba76541cb0a150044327316e22ca84f8d0c2"
        }
      ],
      "licenseConcluded": "NOASSERTION",
      "copyrightText": "NOASSERTION"
    },
    {
      "fileName": "./0003-build-static-or-shared-not-both.patch",
      "SPDXID": "SPDXRef-port-file-2",
      "checksums": [
        {
          "algorithm": "SHA256",
          "checksumValue": "d6026271dcb3d8fc74b41e235620ae31576a798e77aa411c3af8cd9e948c02b1"
        }
      ],
      "licenseConcluded": "NOASSERTION",
      "copyrightText": "NOASSERTION"
    },
    {
      "fileName": "./0004-android-and-mingw-fixes.patch",
      "SPDXID": "SPDXRef-port-file-3",
      "checksums": [
        {
          "algorithm": "SHA256",
          "checksumValue": "37a43eddbcb1b7dde49e7659ae895dfd0ff1df66666c1371ba7d5bfc49d8b438"
        }
      ],
      "licenseConcluded": "NOASSERTION",
      "copyrightText": "NOASSERTION"
    },
    {
      "fileName": "./portfile.cmake",
      "SPDXID": "SPDXRef-port-file-4",
      "checksums": [
        {
          "algorithm": "SHA256",
          "checksumValue": "ac63047b644fa758860dd7ba48ff9a13b058c6f240b8e8d675b8fbba035976be"
        }
      ],
      "licenseConcluded": "NOASSERTION",
      "copyrightText": "NOASSERTION"
    },
    {
      "fileName": "./usage",
      "SPDXID": "SPDXRef-port-file-5",
      "checksums": [
        {
          "algorithm": "SHA256",
          "checksumValue": "be22662327df993eebc437495add75acb365ab18d37c7e5de735d4ea4f5d3083"
        }
      ],
      "licenseConcluded": "NOASSERTION",
      "copyrightText": "NOASSERTION"
    },
    {
      "fileName": "./vcpkg-cmake-wrapper.cmake",
      "SPDXID": "SPDXRef-port-file-6",
      "checksums": [
        {
          "algorithm": "SHA256",
          "checksumValue": "5d49ef2ee6448479c2aad0e5f732e2676eaba0411860f9bebabe6002d66f57d1"
        }
      ],
      "licenseConcluded": "NOASSERTION",
      "copyrightText": "NOASSERTION"
    },
    {
      "fileName": "./vcpkg.json",
      "SPDXID": "SPDXRef-port-file-7",
      "checksums": [
        {
          "algorithm": "SHA256",
          "checksumValue": "bc94e2540efabe36130a806381a001c57194e7de67454ab7ff1e30aa15e6ce23"
        }
      ],
      "licenseConcluded": "NOASSERTION",
      "copyrightText": "NOASSERTION"
    },
    {
      "fileName": "./bin/zlib.pdb",
      "SPDXID": "SPDXRef-binary-file-0",
      "checksums": [
        {
          "algorithm": "SHA256",
          "checksumValue": "4615aa1b221975f7021e60be65ba3ed5425358c712f0e9185170c819813b3686"
        }
      ],
      "licenseConcluded": "NOASSERTION",
      "copyrightText": "NOASSERTION"
    },
    {
      "fileName": "./bin/zlib1.dll",
      "SPDXID": "SPDXRef-binary-file-1",
      "checksums": [
        {
          "algorithm": "SHA256",
          "checksumValue": "37d81d3667faa70598fb86742d09cf2062129aaf60a695e685771d0f27b766b5"
        }
      ],
      "licenseConcluded": "NOASSERTION",
      "copyrightText": "NOASSERTION"
    },
    {
      "fileName": "./BUILD_INFO",
      "SPDXID": "SPDXRef-binary-file-2",
      "checksums": [
        {
          "algorithm": "SHA256",
          "checksumValue": "5e7f821ab4eb804deb535baa7b41edca682d0303cf21a91908c98d5c9a7dcf4d"
        }
      ],
      "licenseConcluded": "NOASSERTION",
      "copyrightText": "NOASSERTION"
    },
    {
      "fileName": "./debug/bin/zlibd.pdb",
      "SPDXID": "SPDXRef-binary-file-3",
      "checksums": [
        {
          "algorithm": "SHA256",
          "checksumValue": "8b2ba81d27a683654de6d5bee6cf1f4f64b2b99eb2b5318405bcd0581be0aef9"
        }
      ],
      "licenseConcluded": "NOASSERTION",
      "copyrightText": "NOASSERTION"
    },
    {
      "fileName": "./debug/bin/zlibd1.dll",
      "SPDXID": "SPDXRef-binary-file-4",
      "checksums": [
        {
          "algorithm": "SHA256",
          "checksumValue": "bc6d12c2b583f293a2d14284e49eb3344bc022d07f09ab899ae82273f91fc76d"
        }
      ],
      "licenseConcluded": "NOASSERTION",
      "copyrightText": "NOASSERTION"
    },
    {
      "fileName": "./debug/lib/pkgconfig/zlib.pc",
      "SPDXID": "SPDXRef-binary-file-5",
      "checksums": [
        {
          "algorithm": "SHA256",
          "checksumValue": "2a87289800864b6fb23a6ab45dfa9ee02b3b58df137a0552f11527fded7c4bd4"
        }
      ],
      "licenseConcluded": "NOASSERTION",
      "copyrightText": "NOASSERTION"
    },
    {
      "fileName": "./debug/lib/zlibd.lib",
      "SPDXID": "SPDXRef-binary-file-6",
      "checksums": [
        {
          "algorithm": "SHA256",
          "checksumValue": "d145749f5ccb8d9399c1bd8c2afc17ebd118e0c6dad6caca33dad2f31536da9e"
        }
      ],
      "licenseConcluded": "NOASSERTION",
      "copyrightText": "NOASSERTION"
    },
    {
      "fileName": "./include/zconf.h",
      "SPDXID": "SPDXRef-binary-file-7",
      "checksums": [
        {
          "algorithm": "SHA256",
          "checksumValue": "bfd95b321f2703c49945c2318ffad47baa82385a4c53d2663bdff75520de1a2d"
        }
      ],
      "licenseConcluded": "NOASSERTION",
      "copyrightText": "NOASSERTION"
    },
    {
      "fileName": "./include/zlib.h",
      "SPDXID": "SPDXRef-binary-file-8",
      "checksums": [
        {
          "algorithm": "SHA256",
          "checksumValue": "a980a0d104198a53cc220c51ab5856e5be901bec8a2d02e0ee79a8754219dfed"
        }
      ],
      "licenseConcluded": "NOASSERTION",
      "copyrightText": "NOASSERTION"
    },
    {
      "fileName": "./lib/pkgconfig/zlib.pc",
      "SPDXID": "SPDXRef-binary-file-9",
      "checksums": [
        {
          "algorithm": "SHA256",
          "checksumValue": "e67499b2faf772fc90701b1ce6d76cb29c1646e38e6f3cac652b1fca80c78f89"
        }
      ],
      "licenseConcluded": "NOASSERTION",
      "copyrightText": "NOASSERTION"
    },
    {
      "fileName": "./lib/zlib.lib",
      "SPDXID": "SPDXRef-binary-file-10",
      "checksums": [
        {
          "algorithm": "SHA256",
          "checksumValue": "266f389a0cfe0a55b7ba374b5d1d4151fa3afcaa66c298a5bd585086a76add4d"
        }
      ],
      "licenseConcluded": "NOASSERTION",
      "copyrightText": "NOASSERTION"
    },
    {
      "fileName": "./share/zlib/copyright",
      "SPDXID": "SPDXRef-binary-file-11",
      "checksums": [
        {
          "algorithm": "SHA256",
          "checksumValue": "845efc77857d485d91fb3e0b884aaa929368c717ae8186b66fe1ed2495753243"
        }
      ],
      "licenseConcluded": "NOASSERTION",
      "copyrightText": "NOASSERTION"
    },
    {
      "fileName": "./share/zlib/usage",
      "SPDXID": "SPDXRef-binary-file-12",
      "checksums": [
        {
          "algorithm": "SHA256",
          "checksumValue": "be22662327df993eebc437495add75acb365ab18d37c7e5de735d4ea4f5d3083"
        }
      ],
      "licenseConcluded": "NOASSERTION",
      "copyrightText": "NOASSERTION"
    },
    {
      "fileName": "./share/zlib/vcpkg-cmake-wrapper.cmake",
      "SPDXID": "SPDXRef-binary-file-13",
      "checksums": [
        {
          "algorithm": "SHA256",
          "checksumValue": "5d49ef2ee6448479c2aad0e5f732e2676eaba0411860f9bebabe6002d66f57d1"
        }
      ],
      "licenseConcluded": "NOASSERTION",
      "copyrightText": "NOASSERTION"
    }
  ]
}
